honest_ml/__init__.py
honest_ml/experiment/__init__.py
honest_ml/experiment/experiment.py
honest_ml/trainer/__init__.py
honest_ml/trainer/analyzer.py
honest_ml/trainer/trainer.py
honest_ml/utils/__init__.py
honest_ml/utils/utils.py
honest_ml/visualizer/__init__.py
honest_ml/visualizer/visualizer.py
honest_ml-0.11.2.dist-info/LICENSE
honest_ml-0.11.2.dist-info/METADATA
honest_ml-0.11.2.dist-info/WHEEL
honest_ml-0.11.2.dist-info/top_level.txt
honest_ml-0.11.2.dist-info/RECORD
