Metadata-Version: 2.1
Name: honest-ml
Version: 0.11.2
Summary: Training for models conforming to the scikit-learn api
Home-page: https://github.com/EricSchles/honest_ml
Author: Eric Schles
Author-email: ericschles@gmail.com
License: MIT
Classifier: License :: OSI Approved :: MIT License
Classifier: Programming Language :: Python :: 3
Classifier: Programming Language :: Python :: 3.6
Classifier: Programming Language :: Python :: 3.7
Classifier: Programming Language :: Python :: 3.8
Classifier: Programming Language :: Python :: 3.9
Classifier: Programming Language :: Python :: 3.10
License-File: LICENSE
Requires-Dist: scikit-learn
Requires-Dist: scipy
Requires-Dist: numpy
Requires-Dist: statsmodels
Requires-Dist: mlxtend
Requires-Dist: pytest
Requires-Dist: seaborn
